__init__.py
pytest_aviator/__init__.py
pytest_aviator/attributes.py
pytest_aviator/runner.py
pytest_aviator-0.1.1.dist-info/LICENSE
pytest_aviator-0.1.1.dist-info/METADATA
pytest_aviator-0.1.1.dist-info/WHEEL
pytest_aviator-0.1.1.dist-info/entry_points.txt
pytest_aviator-0.1.1.dist-info/top_level.txt
pytest_aviator-0.1.1.dist-info/RECORD
