Metadata-Version: 2.1
Name: pytest-aviator
Version: 0.1.1
Summary: Aviator's Flakybot pytest plugin that automatically reruns flaky tests.
Home-page: https://github.com/aviator-co/pytest-aviator
Author: aviator-co
Author-email: engineering@aviator.co
License: MIT
Keywords: pytest plugin flaky tests rerun retry flakybot aviator
Classifier: Development Status :: 4 - Beta
Classifier: Intended Audience :: Developers
Classifier: Topic :: Software Development :: Testing
Classifier: Programming Language :: Python
Classifier: Programming Language :: Python :: 3
Classifier: Programming Language :: Python :: 3.5
Classifier: Programming Language :: Python :: 3.6
Classifier: Programming Language :: Python :: 3.7
Classifier: Programming Language :: Python :: 3.8
Requires-Python: >=3.6
License-File: LICENSE
Requires-Dist: pytest
Requires-Dist: requests
